plspy/__docs__.py
plspy/__init__.py
plspy/_version.py
plspy/core/__init__.py
plspy/core/bootstrap_permutation.py
plspy/core/check_inputs.py
plspy/core/class_functions.py
plspy/core/decorators.py
plspy/core/exceptions.py
plspy/core/gsvd.py
plspy/core/pls.py
plspy/core/pls_classes.py
plspy/core/resample.py
plspy/io/__init__.py
plspy/io/io.py
plspy/tests/__init__.py
plspy/tests/test_class_functions.py
plspy/tests/test_io.py
plspy/visualize/__init__.py
plspy/visualize/visualize.py
plspy/visualize/visualize_classes.py
plspy-0.3.0.dist-info/LICENSE
plspy-0.3.0.dist-info/METADATA
plspy-0.3.0.dist-info/WHEEL
plspy-0.3.0.dist-info/top_level.txt
plspy-0.3.0.dist-info/RECORD
